README.md
setup.py
cursebox/__init__.py
cursebox/__main__.py
cursebox/colors.py
cursebox/constants.py
cursebox/cursebox.py
cursebox/pairs.py
cursebox/palette.py
cursebox/symbols.py
cursebox/utils.py
cursebox_lib.egg-info/PKG-INFO
cursebox_lib.egg-info/SOURCES.txt
cursebox_lib.egg-info/dependency_links.txt
cursebox_lib.egg-info/requires.txt
cursebox_lib.egg-info/top_level.txt