Metadata-Version: 2.1
Name: cursebox-lib
Version: 1.0.1
Summary: Curses made simple
Home-page: https://github.com/Tenchi2xh/cursebox
Author: Tenchi
Author-email: tenchi@team2xh.net
License: UNKNOWN
Project-URL: Documentation, https://cursebox.readthedocs.io/en/latest/
Keywords: terminal,termbox,curses
Platform: UNKNOWN
Classifier: Development Status :: 4 - Beta
Classifier: Programming Language :: Python :: 2.7
Classifier: Programming Language :: Python :: 3.3
Classifier: Programming Language :: Python :: 3.4
Classifier: Programming Language :: Python :: 3.5
Provides-Extra: test
